{
	"processChain": {
		"tasks": {
			"compoundTask": {
				"call": [
					{
						"_class": "info",
						"_tab": "SO",
						"_refid": "PARAMETRES"
					},
					{
						"_class": "option",
						"_tab": "SO",
						"_refid": "DEMANDE_MISE_EN_ROUTE"
					},
					{
						"_class": "option",
						"_tab": "SO",
						"_refid": "DEMANDE_REPOUSSAGE"
					},
					{
						"_class": "option",
						"_tab": "SO",
						"_refid": "DEMANDE_ROULAGE"
					},
					{
						"_class": "option",
						"_tab": "SO",
						"_refid": "TAXI"
					},
					{
						"_class": "info",
						"_tab": "SO",
						"_refid": "TRANSFERT_TOUR1"
					},
					{
						"_class": "option",
						"_tab": "DE",
						"_refid": "CONTACT_TOUR1"
					},
					{
						"_class": "option",
						"_tab": "DE",
						"_refid": "TYPE_ALIGNEMENT"
					},
					{
						"_class": "option",
						"_tab": "DE",
						"_refid": "DECOLLAGE"
					},
					{
						"_class": "option",
						"_tab": "DE",
						"_refid": "TRANSFERT_APP"
					},
					{
						"_class": "option",
						"_tab": "DE",
						"_refid": "CONTACT_APP"
					},
					{
						"_class": "option",
						"_tab": "DE",
						"_refid": "TRANSFERT_CTR"
					},
					{
						"_class": "info",
						"_tab": "CR",
						"_refid": "CONTACT_CTR"
					},
					{
						"_class": "option",
						"_tab": "CR",
						"_refid": "ROUTE"
					},
					{
						"_class": "option",
						"_tab": "CR",
						"_refid": "ROUTE_PILOTE"
					},
					{
						"_class": "info",
						"_tab": "CR",
						"_refid": "NIVEAU"
					},
					{
						"_class": "option",
						"_tab": "CR",
						"_refid": "REGULATION"
					},
					{
						"_class": "option",
						"_tab": "CR",
						"_refid": "TRANSFERT_APP2"
					},
					{
						"_class": "option",
						"_tab": "AP",
						"_refid": "DESCENTE"
					},
					{
						"_class": "option",
						"_tab": "AP",
						"_refid": "REGULATIONBIS"
					},
					{
						"_class": "option",
						"_tab": "AP",
						"_refid": "ATTENTE"
					},
					{
						"_class": "option",
						"_tab": "AP",
						"_refid": "GUIDAGE_RADAR"
					},
					{
						"_class": "option",
						"_tab": "AP",
						"_refid": "APPROCHE"
					},
					{
						"_class": "option",
						"_tab": "AP",
						"_refid": "APPROCHE_VUE"
					},
					{
						"_class": "option",
						"_tab": "AP",
						"_refid": "APPROCHE_VUE_PILOT"
					},
					{
						"_class": "info",
						"_tab": "AP",
						"_refid": "TRANSFERT_TOUR"
					},
					{
						"_class": "info",
						"_tab": "AT",
						"_refid": "CONTACT_TWR"
					},
					{
						"_class": "option",
						"_tab": "AT",
						"_refid": "ATTERRISSAGE"
					},
					{
						"_class": "option",
						"_tab": "AT",
						"_refid": "DEGAGEMENT"
					},
					{
						"_class": "info",
						"_tab": "AT",
						"_refid": "TRANSFERT_SOL"
					},
					{
						"_class": "option",
						"_tab": "AT",
						"_refid": "TAXI2"
					},
					{
						"_class": "info",
						"_tab": "AT",
						"_refid": "PARKING"
					},
					{
						"_class": "info",
						"_tab": "AT",
						"_refid": "QUITTER"
					},
					{
						"_class": "info",
						"_tab": "EX",
						"_refid": "ACCUSEZ"
					},
					{
						"_class": "info",
						"_tab": "EX",
						"_refid": "REPETEA"
					},
					{
						"_class": "info",
						"_tab": "EX",
						"_refid": "REPETEP"
					},
					{
						"_class": "info",
						"_tab": "EX",
						"_refid": "IDENT"
					},
					{
						"_class": "info",
						"_tab": "EX",
						"_refid": "TAUX_MONTEE"
					},
					{
						"_class": "info",
						"_tab": "EX",
						"_refid": "LENTEMENT"
					},
					{
						"_class": "info",
						"_tab": "EX",
						"_refid": "VISUEL"
					},
					{
						"_class": "info",
						"_tab": "EX",
						"_refid": "SILLAGE"
					}
				]
			},
			"spawnTask": [
				{
					"para": [
						{
							"_lang": "fr",
							"_class": "Pilot",
							"__text": "[DEP] [NDEL], [POL], demande paramètres pour le départ, [CAL]."
						},
						{
							"_lang": "fr",
							"_class": "ATC",
							"__text": "[CAL], piste [RWY], [MET], niveau de transition (6_0), il est [HOU]."
						},
						{
							"_lang": "fr",
							"_class": "Pilot",
							"__text": "Piste [RWY], Q_N_H [QNH], [CAL]."
						},
						{
							"_lang": "en",
							"_class": "Pilot",
							"__text": "[DEP] [NDEL], [POL], request departure information, [CAL]."
						},
						{
							"_lang": "en",
							"_class": "ATC",
							"__text": "Runway [RWY], [MET], transition level (6_0), time [HOU]."
						},
						{
							"_lang": "en",
							"_class": "Pilot",
							"__text": "Runway [RWY], Q_N_H [QNH], [CAL]."
						}
					],
					"_id": "PARAMETRES",
					"_name": "Demande paramètres",
					"_short": "Paramètres",
					"_level": "débutant"
				},
				{
					"para": [
						{
							"_lang": "fr",
							"_class": "ATC",
							"__text": "[CAL], [POL], confirmez si capable départ R_N_P (BASIP 5Z)."
						},
						{
							"_lang": "fr",
							"_class": "Pilot",
							"__text": "Départ (BASIP 5Z) impossible cause équipement, [CAL]."
						},
						{
							"_lang": "fr",
							"_class": "ATC",
							"__text": "[CAL], roger, mise en route approuvée, prévoyez un départ conventionnel [STA], montée initiale [NIV], transpondeur [SQU]."
						},
						{
							"_lang": "en",
							"_class": "ATC",
							"__text": "[CAL], [POL], confirm if able R_N_P (BASIP 5Z) departure."
						},
						{
							"_lang": "en",
							"_class": "Pilot",
							"__text": "Unable (BASIP 5Z) departure due equipment, [CAL]."
						},
						{
							"_lang": "en",
							"_class": "ATC",
							"__text": "[CAL], roger, start-up approved, expect [STA] departure, initial climb [NIV], squawk [SQU]."
						}
					],
					"_id": "EST_IL_RNAV",
					"_name": "Capacité RNAV ?",
					"_short": "RNAV ?",
					"_level": "intermédiaire"
				},
				{
					"para": [
						{
							"_lang": "fr",
							"_class": "ATC",
							"__text": "[CAL], [POL], mise en route approuvée, départ (BASIP 5Z), montée initiale [NIV], transpondeur [SQU]."
						},
						{
							"_lang": "fr",
							"_class": "Pilot",
							"__text": "Impossible R_N_P zone terminale{La zone terminale correspond au Terminal Manoeuvring Area (TMA)}, [CAL]."
						},
						{
							"_lang": "fr",
							"_class": "ATC",
							"__text": "[CAL], roger, mise en route approuvée, prévoyez un départ conventionnel [STA], montée initiale [NIV], transpondeur [SQU]."
						},
						{
							"_lang": "en",
							"_class": "ATC",
							"__text": "[CAL], [POL], startup approved, (BASIP 5Z) departure, initial climb [NIV], squawk [SQU]."
						},
						{
							"_lang": "en",
							"_class": "Pilot",
							"__text": "Unable R_N_P terminal area{La zone terminale correspond au Terminal Manoeuvring Area (TMA)}, [CAL]."
						},
						{
							"_lang": "en",
							"_class": "ATC",
							"__text": "[CAL], roger, start-up approved, expect [STA] departure, initial climb [NIV], squawk [SQU]."
						}
					],
					"_id": "NON_RNAV",
					"_name": "MER RNAV capacité conv.",
					"_short": "Non RNAV",
					"_level": "intermédiaire"
				},
				{
					"para": [
						{
							"_lang": "fr",
							"_class": "ATC",
							"__text": "[CAL], [POL], départ omnidirectionnel, piste [RWY], à (800) pieds tournez à (droite) cap [CAP] en montée vers (3000) pieds Q_N_H, transpondeur [SQU]."
						},
						{
							"_lang": "fr",
							"_class": "Pilot",
							"__text": "Départ omnidirectionnel, piste [RWY], à (800) pieds tournez à (droite) cap [CAP] en montée vers (3000) pieds QNH, transpondeur [SQU], [CAL]."
						},
						{
							"_lang": "fr",
							"_class": "ATC",
							"__text": "[CAL], correct, rappelez prêt pour le repoussage sur [DEP] [GND] {ce rappel est nécessaire uniquement en cas de transfert}."
						},
						{
							"_lang": "en",
							"_class": "ATC",
							"__text": "[CAL], [POL], multidirectional departure, runway [RWY], at (800) ft turn (right) [CAP], climb (3000) feet Q_N_H, squawk [SQU]."
						},
						{
							"_lang": "en",
							"_class": "Pilot",
							"__text": "Multidirectional departure, runway [RWY], at (800) ft turn (right) [CAP], climb (3000) feet Q_N_H squawk [SQU], [CAL]."
						},
						{
							"_lang": "en",
							"_class": "ATC",
							"__text": "[CAL], correct, report ready for push-back [DEP] [GND] {ce rappel est nécessaire uniquement en cas de transfert}."
						}
					],
					"_id": "MER_OMNI",
					"_name": "MER omnidirectionnel",
					"_short": "Omni",
					"_level": "intermédiaire"
				},
				{
					"para": [
						{
							"span": {
								"_class": "AVA",
								"__text": ", CTOT [HDIFF] {Créneau de Départ, décollage entre [HDIFF5M] et [HDIFF10P]}"
							},
							"_lang": "fr",
							"_class": "ATC",
							"__text": "[CAL], [POL], mise en route approuvée, CTOT [HDIFF]{Créneau de Départ, décollage entre [HDIFF5M] et [HDIFF10P]}, départ [STA], montée initiale [NIV], transpondeur [SQU]."
						},
						{
							"_lang": "fr",
							"_class": "Pilot",
							"__text": "Mise en route approuvée, CTOT [HDIFF], départ [STA], montée initiale [NIV], transpondeur [SQU], [CAL]."
						},
						{
							"_lang": "fr",
							"_class": "ATC",
							"__text": "[CAL], correct, rappelez prêt pour le repoussage sur [DEP] [GND] {ce rappel est nécessaire uniquement en cas de transfert}."
						},
						{
							"_lang": "en",
							"_class": "ATC",
							"__text": "[CAL], [POL], startup approved, C_TOT [HDIFF]{Slot time, take off between [HDIFF5M] and [HDIFF10P]}, [STA] departure, initial climb [NIV], squawk [SQU]."
						},
						{
							"_lang": "en",
							"_class": "Pilot",
							"__text": "Startup approved, C_TOT [HDIFF], [STA] departure, initial climb [NIV], squawk [SQU], [CAL]."
						},
						{
							"_lang": "en",
							"_class": "ATC",
							"__text": "[CAL], correct, report ready for push-back [DEP] [GND] {ce rappel est nécessaire uniquement en cas de transfert}."
						}
					],
					"_id": "MER_APPROUVEE",
					"_name": "MER approuvée",
					"_short": "Approuvée",
					"_level": "intermédiaire"
				},
				{
					"para": [
						{
							"_lang": "fr",
							"_class": "ATC",
							"__text": "[CAL], prévoyez mise en route [HDIFF] cause trafic à l'arrivée."
						},
						{
							"_lang": "en",
							"_class": "ATC",
							"__text": "[CAL], expect start-up time [HDIFF] due inbound traffic."
						}
					],
					"_id": "MER_DIFFEREE",
					"_name": "MER différée",
					"_short": "Différée",
					"_level": "débutant"
				},
				{
					"para": [
						{
							"_lang": "fr",
							"_class": "ATC",
							"__text": "[CAL], repoussage approuvé."
						},
						{
							"_lang": "en",
							"_class": "ATC",
							"__text": "[CAL], push-back approved."
						},
						{
							"_lang": "fr",
							"_class": "Pilot",
							"__text": "Je repousse, [CAL]."
						},
						{
							"_lang": "en",
							"_class": "Pilot",
							"__text": "Pushing back, [CAL]."
						}
					],
					"_id": "REPOUSSAGE_STANDARD",
					"_name": "Repoussage standard",
					"_short": "Standard",
					"_level": "débutant"
				},
				{
					"para": [
						{
							"_lang": "fr",
							"_class": "ATC",
							"__text": "[CAL], en fonction du Boeing 737 passant derrière vous, repoussage approuvé."
						},
						{
							"_lang": "fr",
							"_class": "Pilot",
							"__text": "Je repousse en fonction du Boeing 737 en vue, [CAL]."
						},
						{
							"_lang": "en",
							"_class": "ATC",
							"__text": "[CAL], according to Boeing 7 3 7 taxiing behind you, pushback approved."
						},
						{
							"_lang": "en",
							"_class": "Pilot",
							"__text": "Push-back approved, according to 737 in sight, [CAL]."
						}
					],
					"_id": "REPOUSSAGE_CONDITIONNEL",
					"_name": "Repoussage conditionnel",
					"_short": "Conditionnel",
					"_level": "débutant"
				},
				{
					"para": [
						{
							"_lang": "fr",
							"_class": "ATC",
							"__text": "[CAL], roulez point d'attente piste [RWY] via [VOI] [HLD]."
						},
						{
							"_lang": "fr",
							"_class": "Pilot",
							"__text": "Je roule point d'attente piste [RWY] via [VOI] [HLD], [CAL]."
						},
						{
							"_lang": "en",
							"_class": "ATC",
							"__text": "[CAL], taxi holding point runway [RWY] via [VOI] [HLD]."
						},
						{
							"_lang": "en",
							"_class": "Pilot",
							"__text": "Taxiing holding point runway [RWY] via [VOI] [HLD], [CAL]."
						}
					],
					"_id": "ROULAGE_AUTORISE",
					"_name": "Roulage standard",
					"_short": "Standard",
					"_level": "débutant"
				},
				{
					"para": [
						{
							"_lang": "fr",
							"_class": "ATC",
							"__text": "Contactez [DEP] [TWR]."
						},
						{
							"_lang": "fr",
							"_class": "Pilot",
							"__text": "Je contacte [DEP] [TWR], merci, [CAL]."
						},
						{
							"_lang": "en",
							"_class": "ATC",
							"__text": "Contact [DEP] [TWR]."
						},
						{
							"_lang": "en",
							"_class": "Pilot",
							"__text": "[DEP] [TWR], thank you, [CAL]."
						}
					],
					"_id": "TRANSFERT_TOUR1",
					"_name": "Transfert tour",
					"_short": "Tr TWR",
					"_level": "débutant"
				},
				{
					"para": [
						{
							"_lang": "fr",
							"_class": "ATC",
							"__text": "[CAL], laissez passer l'Airbus A320 Air-France venant de votre droite, roulez point d'attente piste [RWY]."
						},
						{
							"_lang": "fr",
							"_class": "Pilot",
							"__text": "Je laisse passer l'Airbus A320 Air-France venant de notre droite et roule point d'attente piste [RWY], [CAL]."
						},
						{
							"_lang": "en",
							"_class": "ATC",
							"__text": "[CAL], give way to Air-France Airbus coming from your right, taxi holding point runway [RWY]."
						},
						{
							"_lang": "en",
							"_class": "Pilot",
							"__text": "Giving way to Air-France Airbus coming from our right, taxiing holding point runway [RWY], [CAL]."
						}
					],
					"_id": "ROULAGE_TRAFIC",
					"_name": "Roulage avec trafic",
					"_short": "Trafic",
					"_level": "débutant"
				},
				{
					"para": [
						{
							"_lang": "fr",
							"_class": "ATC",
							"__text": "[CAL], remontez piste [RWY], alignez-vous et attendez."
						},
						{
							"_lang": "fr",
							"_class": "Pilot",
							"__text": "Je remonte piste [RWY], je m'aligne et attends, [CAL]."
						},
						{
							"_lang": "en",
							"_class": "ATC",
							"__text": "[CAL], backtrack runway [RWY], line up and wait."
						},
						{
							"_lang": "en",
							"_class": "Pilot",
							"__text": "Backtracking runway [RWY], lining up and waiting, [CAL]."
						}
					],
					"_id": "REMONTEE_PISTE",
					"_name": "Remontée de piste",
					"_short": "Remontée",
					"_level": "intermédiaire"
				},
				{
					"para": [
						{
							"_lang": "fr",
							"_class": "ATC",
							"__text": "[CAL], A_T_R en finale, rappelez en vue."
						},
						{
							"_lang": "fr",
							"_class": "Pilot",
							"__text": "A_T_R en vue, [CAL]."
						},
						{
							"_lang": "fr",
							"_class": "ATC",
							"__text": "[CAL], derrière A_T_R en finale, alignez-vous et attendez piste [RWY] derrière."
						},
						{
							"_lang": "fr",
							"_class": "Pilot",
							"__text": "Derrière A_T_R en finale, je m'aligne et attends piste [RWY] derrière, [CAL]."
						},
						{
							"_lang": "en",
							"_class": "ATC",
							"__text": "[CAL], A_T_R on final, report in sight."
						},
						{
							"_lang": "en",
							"_class": "Pilot",
							"__text": "A_T_R in sight, [CAL]."
						},
						{
							"_lang": "en",
							"_class": "ATC",
							"__text": "[CAL], behind A_T_R on final, line up and wait runway [RWY] behind."
						},
						{
							"_lang": "en",
							"_class": "Pilot",
							"__text": "Behind A_T_R on final, lining up and waiting runway [RWY], [CAL]."
						}
					],
					"_id": "ALIGNEMENT_APRES_AVION_FINAL",
					"_name": "Alignement après final",
					"_short": "Après final",
					"_level": "débutant"
				},
				{
					"para": [
						{
							"_lang": "fr",
							"_class": "ATC",
							"__text": "[CAL], alignez-vous et attendez piste [RWY]."
						},
						{
							"_lang": "fr",
							"_class": "Pilot",
							"__text": "Je m'aligne et attends piste [RWY], [CAL]."
						},
						{
							"_lang": "en",
							"_class": "ATC",
							"__text": "[CAL], line up and wait runway [RWY]."
						},
						{
							"_lang": "en",
							"_class": "Pilot",
							"__text": "Lining up and waiting runway [RWY], [CAL]."
						}
					],
					"_id": "ALIGNEMENT",
					"_name": "Alignement simple",
					"_short": "Simple",
					"_level": "débutant"
				},
				{
					"para": [
						{
							"_lang": "fr",
							"_class": "ATC",
							"__text": "[CAL], alignez-vous et attendez piste [RWY], intersection W7, numéro deux derrière un Boeing 737."
						},
						{
							"_lang": "fr",
							"_class": "Pilot",
							"__text": "Je m'aligne et attends piste [RWY], intersection W7, [CAL], numéro deux derrière un Boeing 737."
						},
						{
							"_lang": "en",
							"_class": "ATC",
							"__text": "[CAL], line up and wait runway [RWY], intersection W7, number two behind a 737."
						},
						{
							"_lang": "en",
							"_class": "Pilot",
							"__text": "Lining up and waiting runway [RWY], intersection W7, number two behind a 737, [CAL]."
						}
					],
					"_id": "ALIGNEMENT_POS2",
					"_name": "Alignement position 2",
					"_short": "Numéro 2",
					"_level": "débutant"
				},
				{
					"para": [
						{
							"_lang": "fr",
							"_class": "ATC",
							"__text": "[CAL], maintenez avant piste [RWY] taxiway [HLD]."
						},
						{
							"_lang": "fr",
							"_class": "Pilot",
							"__text": "Je maintiens avant piste [RWY] taxiway [HLD], [CAL]."
						},
						{
							"_lang": "en",
							"_class": "ATC",
							"__text": "[CAL], hold short of runway [RWY], taxiway [HLD]."
						},
						{
							"_lang": "en",
							"_class": "Pilot",
							"__text": "Maintaining short of runway [RWY], taxiway [HLD], [CAL]."
						}
					],
					"_id": "MAINTIEN_ARRET",
					"_name": "Maintien point d'attente",
					"_short": "Maintien",
					"_level": "débutant"
				},
				{
					"para": [
						{
							"_lang": "fr",
							"_class": "ATC",
							"__text": "[CAL], êtes-vous prêt pour un départ immédiat ?"
						},
						{
							"_lang": "fr",
							"_class": "Pilot",
							"__text": "Affirm, [CAL]."
						},
						{
							"_lang": "fr",
							"_class": "ATC",
							"__text": "[CAL], alignez-vous piste [RWY], autorisé décollage immédiat, vent 0_50 degrés 10 nœuds."
						},
						{
							"_lang": "fr",
							"_class": "Pilot",
							"__text": "Je m'aligne piste [RWY] et je décolle, [CAL]."
						},
						{
							"_lang": "en",
							"_class": "ATC",
							"__text": "[CAL], say if ready for immediate departure."
						},
						{
							"_lang": "en",
							"_class": "Pilot",
							"__text": "Affirm, [CAL]."
						},
						{
							"_lang": "en",
							"_class": "ATC",
							"__text": "[CAL], line up runway [RWY] and cleared for immediate take-off, wind 0_5_0 degrees, 10 knots."
						},
						{
							"_lang": "en",
							"_class": "Pilot",
							"__text": "Lining up runway [RWY] and taking-off, [CAL]."
						}
					],
					"_id": "DECOLLAGE_IMMEDIAT",
					"_name": "Décollage immédiat",
					"_short": "Immédiat",
					"_level": "intermédiaire"
				},
				{
					"para": [
						{
							"_lang": "fr",
							"_class": "ATC",
							"__text": "[CAL], contactez [DEP] [APP]."
						},
						{
							"_lang": "fr",
							"_class": "Pilot",
							"__text": "Je contacte [DEP] [APP], merci, [CAL]."
						},
						{
							"_lang": "en",
							"_class": "ATC",
							"__text": "[CAL], contact [DEP] [APP]."
						},
						{
							"_lang": "en",
							"_class": "Pilot",
							"__text": "[DEP] [APP], thank you, [CAL]."
						}
					],
					"_id": "TRANSFERT_SIMPLE",
					"_name": "Transfert contrôleur",
					"_short": "Tr APP",
					"_level": "débutant"
				},
				{
					"para": [
						{
							"_lang": "fr",
							"_class": "ATC",
							"__text": "[CAL], contactez [FIR] [CTR]."
						},
						{
							"_lang": "fr",
							"_class": "Pilot",
							"__text": "Je contacte [FIR] [NCTR], merci, [CAL]."
						},
						{
							"_lang": "en",
							"_class": "ATC",
							"__text": "[CAL], contact [FIR] [CTR]."
						},
						{
							"_lang": "en",
							"_class": "Pilot",
							"__text": "[FIR] [NCTR], thank you, [CAL]."
						}
					],
					"_id": "TRANSFERT_SIMPLE_CTR",
					"_name": "Transfert contrôleur",
					"_short": "Tr CTR",
					"_level": "débutant"
				},
				{
					"para": [
						{
							"_lang": "fr",
							"_class": "ATC",
							"__text": "[CAL], contactez [ARR] [GND]."
						},
						{
							"_lang": "fr",
							"_class": "Pilot",
							"__text": "[ARR] [GND], merci, [CAL]."
						},
						{
							"_lang": "en",
							"_class": "ATC",
							"__text": "[CAL], contact [ARR] [GND]."
						},
						{
							"_lang": "en",
							"_class": "Pilot",
							"__text": "[ARR] [GND], thank you, [CAL]."
						}
					],
					"_id": "TRANSFERT_SOL",
					"_name": "Transfert contrôleur",
					"_short": "Tr GND",
					"_level": "débutant"
				},
				{
					"para": [
						{
							"_lang": "fr",
							"_class": "ATC",
							"__text": "[CAL], contactez [ARR] [TWR]."
						},
						{
							"_lang": "fr",
							"_class": "Pilot",
							"__text": "[ARR] [TWR], merci, [CAL]."
						},
						{
							"_lang": "en",
							"_class": "ATC",
							"__text": "[CAL], contact [ARR] [TWR]."
						},
						{
							"_lang": "en",
							"_class": "Pilot",
							"__text": "[ARR] [TWR], thank you, [CAL]."
						}
					],
					"_id": "TRANSFERT_TOUR",
					"_name": "Transfert tour",
					"_short": "Tr TWR",
					"_level": "débutant"
				},
				{
					"para": [
						{
							"_lang": "fr",
							"_class": "ATC",
							"__text": "[CAL], service du contrôle terminé, auto-information, 122 décimale 8."
						},
						{
							"_lang": "fr",
							"_class": "Pilot",
							"__text": "Auto-information, 122 décimale 8, merci, [CAL]."
						},
						{
							"_lang": "en",
							"_class": "ATC",
							"__text": "[CAL], control service terminated, air-to-air frequency, one hundred twenty two decimal eight."
						},
						{
							"_lang": "en",
							"_class": "Pilot",
							"__text": "Air-to-air frequency, one hundred twenty two decimal eight, thank you, [CAL]."
						}
					],
					"_id": "TRANSFERT_UNICOM",
					"_name": "Fin service",
					"_short": "Fin",
					"_level": "débutant"
				},
				{
					"para": [
						{
							"_lang": "fr",
							"_class": "ATC",
							"__text": "[CAL], montez via SID niveau [NIV]."
						},
						{
							"_lang": "en",
							"_class": "ATC",
							"__text": "[CAL], climb via SID level [NIV]."
						},
						{
							"_lang": "fr",
							"_class": "Pilot",
							"__text": "Je monte via SID niveau [NIV], [CAL]."
						},
						{
							"_lang": "en",
							"_class": "Pilot",
							"__text": "Climbing via SID level [NIV], [CAL]."
						}
					],
					"_id": "CONFIRMATION_SID",
					"_name": "Confirmation SID",
					"_short": "Conf SID",
					"_level": "débutant"
				},
				{
					"para": [
						{
							"_lang": "fr",
							"_class": "ATC",
							"__text": "[CAL], procédez direct [WPT], montez via SID niveau [NIV]."
						},
						{
							"_lang": "fr",
							"_class": "Pilot",
							"__text": "Direct [WPT], je monte via SID niveau [NIV], [CAL]."
						},
						{
							"_lang": "en",
							"_class": "ATC",
							"__text": "[CAL], proceed direct [WPT], climb via SID level [NIV]."
						},
						{
							"_lang": "en",
							"_class": "Pilot",
							"__text": "Proceed direct [WPT], climb via SID level [NIV], [CAL]."
						}
					],
					"_id": "DIRECT_WPT",
					"_name": "Direct waypoint",
					"_short": "Direct",
					"_level": "débutant"
				},
				{
					"para": [
						{
							"_lang": "fr",
							"_class": "ATC",
							"__text": "[CAL], stoppez la montée niveau [NIV]."
						},
						{
							"_lang": "fr",
							"_class": "Pilot",
							"__text": "Je stoppe la montée niveau [NIV], [CAL]."
						},
						{
							"_lang": "en",
							"_class": "ATC",
							"__text": "[CAL], stop climbing level [NIV]."
						},
						{
							"_lang": "en",
							"_class": "Pilot",
							"__text": "Stopping climb level [NIV], [CAL]."
						}
					],
					"_id": "MONTEE_DIFFEREE",
					"_name": "Montée stoppée",
					"_short": "Stop",
					"_level": "débutant"
				},
				{
					"para": [
						{
							"_lang": "fr",
							"_class": "ATC",
							"__text": "[CAL], montez niveau [NIV]."
						},
						{
							"_lang": "fr",
							"_class": "Pilot",
							"__text": "Je monte niveau [NIV], [CAL]."
						},
						{
							"_lang": "en",
							"_class": "ATC",
							"__text": "[CAL], climb level [NIV]."
						},
						{
							"_lang": "en",
							"_class": "Pilot",
							"__text": "Climbing level [NIV], [CAL]."
						}
					],
					"_id": "NIVEAU",
					"_name": "Changement de niveau",
					"_short": "Niveau",
					"_level": "débutant"
				},
				{
					"para": [
						{
							"_lang": "fr",
							"_class": "ATC",
							"__text": "[CAL], direct [WPT]."
						},
						{
							"_lang": "fr",
							"_class": "Pilot",
							"__text": "Direct [WPT], [CAL]."
						},
						{
							"_lang": "en",
							"_class": "ATC",
							"__text": "[CAL], direct [WPT]."
						},
						{
							"_lang": "en",
							"_class": "Pilot",
							"__text": "Direct [WPT], [CAL]."
						}
					],
					"_id": "DIRECT",
					"_name": "Direct",
					"_short": "Direct",
					"_level": "intermédiaire"
				},
				{
					"para": [
						{
							"_lang": "fr",
							"_class": "ATC",
							"__text": "[CAL], changement de route, [WPT]."
						},
						{
							"_lang": "fr",
							"_class": "Pilot",
							"__text": "Changement de route, [WPT], [CAL]."
						},
						{
							"_lang": "en",
							"_class": "ATC",
							"__text": "[CAL], route amendment, [WPT]."
						},
						{
							"_lang": "en",
							"_class": "Pilot",
							"__text": "Route amendement, [WPT], [CAL]."
						}
					],
					"_id": "ROUTE_CONTROLEUR",
					"_name": "Nouvelle route",
					"_short": "Route",
					"_level": "intermédiaire"
				},
				{
					"para": [
						{
							"_lang": "fr",
							"_class": "ATC",
							"__text": "[CAL], direct [WPT] approuvé."
						},
						{
							"_lang": "fr",
							"_class": "Pilot",
							"__text": "Direct [WPT], [CAL]."
						},
						{
							"_lang": "en",
							"_class": "ATC",
							"__text": "[CAL], direct [WPT] approuved."
						},
						{
							"_lang": "en",
							"_class": "Pilot",
							"__text": "Direct [WPT], [CAL]."
						}
					],
					"_id": "ROUTE_POSITIVE",
					"_name": "Route acceptée",
					"_short": "Acceptée",
					"_level": "intermédiaire"
				},
				{
					"para": [
						{
							"_lang": "fr",
							"_class": "ATC",
							"__text": "[CAL], changement de route impossible cause régulation de trafic."
						},
						{
							"_lang": "fr",
							"_class": "Pilot",
							"__text": "Roger, [CAL]."
						},
						{
							"_lang": "en",
							"_class": "ATC",
							"__text": "[CAL],route amendment unable due flow control."
						},
						{
							"_lang": "en",
							"_class": "Pilot",
							"__text": "Roger, [CAL]."
						}
					],
					"_id": "ROUTE_NEGATIVE",
					"_name": "Route refusée",
					"_short": "Refusée",
					"_level": "intermédiaire"
				},
				{
					"para": [
						{
							"_lang": "fr",
							"_class": "ATC",
							"__text": "[CAL], trafic à 11 heures, 4 nautiques, gauche vers droite, Airbus heavy, 1000 pieds plus haut."
						},
						{
							"i": "et dès acquisition visuelle",
							"_lang": "fr",
							"_class": "Pilot",
							"__text": "Roger, [CAL] (\n)."
						},
						{
							"_lang": "fr",
							"_class": "Pilot",
							"__text": "Airbus en vue, 1000 pieds plus haut, [CAL]."
						},
						{
							"_lang": "en",
							"_class": "ATC",
							"__text": "[CAL],traffic 11 o'clock 4 miles, left to right, heavy Airbus, 1000 feet above."
						},
						{
							"i": "et dès acquisition visuelle",
							"_lang": "en",
							"_class": "Pilot",
							"__text": "Roger, [CAL] (\n)."
						},
						{
							"_lang": "en",
							"_class": "Pilot",
							"__text": "Airbus in sight, 1000 feet above, [CAL]."
						}
					],
					"_id": "TRAFIC",
					"_name": "Trafic",
					"_short": "Trafic",
					"_level": "intermédiaire"
				},
				{
					"para": [
						{
							"_lang": "fr",
							"_class": "ATC",
							"__text": "[CAL], descendez niveau [NIV]."
						},
						{
							"_lang": "fr",
							"_class": "Pilot",
							"__text": "Je descends niveau [NIV], [CAL]."
						},
						{
							"_lang": "en",
							"_class": "ATC",
							"__text": "[CAL], descend level [NIV]."
						},
						{
							"_lang": "en",
							"_class": "Pilot",
							"__text": "Descending level [NIV], [CAL]."
						}
					],
					"_id": "DESCENTE_IMMEDIATE",
					"_name": "Descente immédiate",
					"_short": "Descente",
					"_level": "débutant"
				},
				{
					"para": [
						{
							"_lang": "fr",
							"_class": "ATC",
							"__text": "[CAL], quand prêt, descendez niveau [NIV]."
						},
						{
							"_lang": "fr",
							"_class": "Pilot",
							"__text": "Quand prêt, je descends niveau [NIV], [CAL]."
						},
						{
							"_lang": "fr",
							"_class": "Pilot",
							"__text": "[CAL], libère le niveau XXX en descente au niveau [NIV]."
						},
						{
							"_lang": "fr",
							"_class": "ATC",
							"__text": "[CAL], roger."
						},
						{
							"_lang": "en",
							"_class": "ATC",
							"__text": "[CAL], when ready, descend level [NIV]."
						},
						{
							"_lang": "en",
							"_class": "Pilot",
							"__text": "Descending level [NIV] when ready, [CAL]."
						},
						{
							"_lang": "en",
							"_class": "Pilot",
							"__text": "[CAL], leaving level XXX, descending level [NIV]."
						},
						{
							"_lang": "en",
							"_class": "ATC",
							"__text": "[CAL], roger."
						}
					],
					"_id": "DESCENTE_DELAI",
					"_name": "Descente avec délai",
					"_short": "Délai",
					"_level": "intermédiaire"
				},
				{
					"para": [
						{
							"_lang": "fr",
							"_class": "ATC",
							"__text": "[CAL], descendez via [STA] niveau [NIV]."
						},
						{
							"_lang": "fr",
							"_class": "Pilot",
							"__text": "Je descends via [STA] niveau [NIV], [CAL]."
						},
						{
							"_lang": "en",
							"_class": "ATC",
							"__text": "[CAL], descend via [STA] level [NIV]."
						},
						{
							"_lang": "en",
							"_class": "Pilot",
							"__text": "Descending via [STA] level [NIV], [CAL]."
						}
					],
					"_id": "APPROCHE_STAR",
					"_name": "Approche STAR",
					"_short": "STAR",
					"_level": "débutant"
				},
				{
					"para": [
						{
							"_lang": "fr",
							"_class": "ATC",
							"__text": "[CAL], procédez direct [WPT], descendez via [STA] niveau [NIV]."
						},
						{
							"_lang": "fr",
							"_class": "Pilot",
							"__text": "Direct [WPT] je descends via [STA] niveau [NIV], [CAL]."
						},
						{
							"_lang": "en",
							"_class": "ATC",
							"__text": "[CAL], proceed direct [WPT] descend via [STA] level [NIV]."
						},
						{
							"_lang": "en",
							"_class": "Pilot",
							"__text": "Direct [WPT] descending via [STA] level [NIV], [CAL]."
						}
					],
					"_id": "APPROCHE_DIRECT",
					"_name": "Direct dans STAR",
					"_short": "Direct STAR",
					"_level": "intermédiaire"
				},
				{
					"para": [
						{
							"_lang": "fr",
							"_class": "ATC",
							"__text": "[CAL], quelle est votre vitesse ?"
						},
						{
							"_lang": "fr",
							"_class": "Pilot",
							"__text": "[VIT] nœuds, [CAL]."
						},
						{
							"_lang": "fr",
							"_class": "ATC",
							"__text": "[CAL], vitesse [VIT] nœuds pour séquencement."
						},
						{
							"_lang": "fr",
							"_class": "Pilot",
							"__text": "[VIT] nœuds, [CAL]."
						},
						{
							"_lang": "en",
							"_class": "ATC",
							"__text": "[CAL], say speed?"
						},
						{
							"_lang": "en",
							"_class": "Pilot",
							"__text": "[VIT] knots, [CAL]."
						},
						{
							"_lang": "en",
							"_class": "ATC",
							"__text": "[CAL], speed [VIT] knots for sequencing."
						},
						{
							"_lang": "en",
							"_class": "Pilot",
							"__text": "[VIT] knots, [CAL]."
						}
					],
					"_id": "VITESSE",
					"_name": "Vitesse",
					"_short": "Vitesse",
					"_level": "intermédiaire"
				},
				{
					"para": [
						{
							"_lang": "fr",
							"_class": "ATC",
							"__text": "[CAL], réduisez vitesse mini en lisse."
						},
						{
							"_lang": "fr",
							"_class": "Pilot",
							"__text": "Je réduis (220) nœuds, [CAL]."
						},
						{
							"_lang": "en",
							"_class": "ATC",
							"__text": "[CAL], reduce minimum clean speed."
						},
						{
							"_lang": "en",
							"_class": "Pilot",
							"__text": "Reducing (220) knots, [CAL]."
						}
					],
					"_id": "REDUCTION_VITESSE",
					"_name": "Réduction vitesse",
					"_short": "Réduire",
					"_level": "intermédiaire"
				},
				{
					"para": [
						{
							"_lang": "fr",
							"_class": "ATC",
							"__text": "[CAL], tournez à (droite) cap [CAP]."
						},
						{
							"_lang": "fr",
							"_class": "Pilot",
							"__text": "Je tourne à (droite) cap [CAP], [CAL]."
						},
						{
							"_lang": "en",
							"_class": "ATC",
							"__text": "[CAL], turn (right) heading [CAP]."
						},
						{
							"_lang": "en",
							"_class": "Pilot",
							"__text": "Turning (right) heading [CAP], [CAL]."
						}
					],
					"_id": "CHANGEMENT_CAP",
					"_name": "Nouveau cap",
					"_short": "Cap",
					"_level": "intermédiaire"
				},
				{
					"para": [
						{
							"_lang": "fr",
							"_class": "ATC",
							"__text": "[CAL], tournez à (droite) cap [CAP], descendez [NIV] pieds Q_N_H [QNH]."
						},
						{
							"_lang": "fr",
							"_class": "Pilot",
							"__text": "Je tourne à (droite) cap [CAP], je descends [NIV] pieds Q_N_H [QNH], [CAL]."
						},
						{
							"_lang": "en",
							"_class": "ATC",
							"__text": "[CAL], turn (right) heading [CAP], descend [NIV] feet Q_N_H [QNH]."
						},
						{
							"_lang": "en",
							"_class": "Pilot",
							"__text": "Descending [NIV] feet Q_N_H [QNH], turning (right) heading [CAP], [CAL]."
						}
					],
					"_id": "CHANGEMENT_NIVEAU_CAP",
					"_name": "Changements cap et niveau",
					"_short": "Cap et niveau",
					"_level": "intermédiaire"
				},
				{
					"para": [
						{
							"_lang": "fr",
							"_class": "ATC",
							"__text": "[CAL], tournez à (droite) cap [CAP], autorisé approche I_L_S piste [RWY]."
						},
						{
							"_lang": "fr",
							"_class": "Pilot",
							"__text": "Je tourne à (droite) cap [CAP], autorisé approche I_L_S piste [RWY], [CAL]."
						},
						{
							"_lang": "en",
							"_class": "ATC",
							"__text": "[CAL], turn (right) heading [CAP], cleared I_L_S approach runway [RWY]."
						},
						{
							"_lang": "en",
							"_class": "Pilot",
							"__text": "Turning (right) heading [CAP], cleared I_L_S approach runway [RWY], [CAL]."
						}
					],
					"_id": "INTERCEPTION_ILS",
					"_name": "Cap d'interception ILS",
					"_short": "CAP ILS",
					"_level": "débutant"
				},
				{
					"para": [
						{
							"_lang": "fr",
							"_class": "ATC",
							"__text": "[CAL], autorisé jusqu’à [STA], attendez comme publié niveau [NIV], pour régulation."
						},
						{
							"_lang": "fr",
							"_class": "Pilot",
							"__text": "J'attends à [STA], niveau [NIV], [CAL]. (puis...)"
						},
						{
							"_lang": "en",
							"_class": "ATC",
							"__text": "[CAL], cleared to [STA], hold as published at level [NIV], due regulation."
						},
						{
							"_lang": "en",
							"_class": "Pilot",
							"__text": "Holding at [STA], level [NIV], [CAL]. (puis...)"
						},
						{
							"_lang": "fr",
							"_class": "ATC",
							"__text": "[CAL], descendez [NIV] pieds, Q_N_H [QNH], HAP 32."
						},
						{
							"_lang": "fr",
							"_class": "Pilot",
							"__text": "Je descends [NIV] pieds, Q_N_H [QNH], HAP 32, [CAL]."
						},
						{
							"_lang": "en",
							"_class": "ATC",
							"__text": "[CAL], descend [NIV] feet, Q_N_H [QNH], estimated approach time 32."
						},
						{
							"_lang": "en",
							"_class": "Pilot",
							"__text": "Descending [NIV] feet, Q_N_H [QNH], estimated approach time 32, [CAL]."
						}
					],
					"_id": "ATTENTE_PUBLIEE",
					"_name": "Attente publiée",
					"_short": "Publiée",
					"_level": "intermédiaire"
				},
				{
					"para": [
						{
							"_lang": "fr",
							"_class": "ATC",
							"__text": "[CAL], attendez à [STA], niveau [NIV], rapprochement [CAP] degrés, virages à (droite), éloignement 1 minute, vitesse [VIT] nœuds."
						},
						{
							"_lang": "fr",
							"_class": "Pilot",
							"__text": "J'attends à [STA], niveau [NIV], rapprochement [CAP] degrés, virages à (droite), éloignement 1 minute, vitesse [VIT] nœuds, [CAL]."
						},
						{
							"_lang": "en",
							"_class": "ATC",
							"__text": "[CAL], hold at [STA], level [NIV], inbound track [CAP] degrees, right-hand pattern, outbound time 1 minute, speed [VIT] knots."
						},
						{
							"_lang": "en",
							"_class": "Pilot",
							"__text": "Holding at [STA], level [NIV], inbound track [CAP] degrees, right-hand pattern, outbound time 1 minute, speed [VIT] knots, [CAL]."
						}
					],
					"_id": "ATTENTE_PARAMETRES",
					"_name": "Attente non publiée",
					"_short": "Non publiée",
					"_level": "intermédiaire"
				},
				{
					"para": [
						{
							"_lang": "fr",
							"_class": "ATC",
							"__text": "[CAL], autorisé approche I_L_S piste [RWY]."
						},
						{
							"_lang": "fr",
							"_class": "Pilot",
							"__text": "Autorisé approche I_L_S piste [RWY], [CAL]."
						},
						{
							"_lang": "en",
							"_class": "ATC",
							"__text": "[CAL], cleared I_L_S approach runway [RWY]."
						},
						{
							"_lang": "en",
							"_class": "Pilot",
							"__text": "Cleared I_L_S approach runway [RWY], [CAL]."
						}
					],
					"_id": "APPROCHE_AUTORISE",
					"_name": "Approche autorisée",
					"_short": "Autorisée",
					"_level": "débutant"
				},
				{
					"para": [
						{
							"_lang": "fr",
							"_class": "Pilot",
							"__text": "Affirm, [CAL]."
						},
						{
							"_lang": "fr",
							"_class": "ATC",
							"__text": "[CAL], avez-vous visuel sur trafic précédent ?"
						},
						{
							"_lang": "fr",
							"_class": "Pilot",
							"__text": "Affirm, [CAL]."
						},
						{
							"_lang": "fr",
							"_class": "ATC",
							"__text": "[CAL], autorisé approche à vue piste [RWY], assurez votre séparation avec (Fokker 70) devant vous."
						},
						{
							"_lang": "fr",
							"_class": "Pilot",
							"__text": "Autorisé approche à vue piste [RWY], [CAL]."
						},
						{
							"_lang": "en",
							"_class": "Pilot",
							"__text": "Affirm, [CAL]."
						},
						{
							"_lang": "en",
							"_class": "ATC",
							"__text": "[CAL], have you visual contact on preceding traffic ?"
						},
						{
							"_lang": "en",
							"_class": "Pilot",
							"__text": "Affirm, [CAL]."
						},
						{
							"_lang": "en",
							"_class": "ATC",
							"__text": "[CAL], cleared visual approach runway [RWY], maintain own separation from preceding Fokker 70."
						},
						{
							"_lang": "en",
							"_class": "Pilot",
							"__text": "Cleared visual approach runway [RWY], [CAL]."
						}
					],
					"_id": "TRAFIC_MVL",
					"_name": "Accepte avec info trafic",
					"_short": "Trafic",
					"_level": "intermédiaire"
				},
				{
					"para": [
						{
							"_lang": "fr",
							"_class": "ATC",
							"__text": "[CAL], autorisé approche à vue piste [RWY]."
						},
						{
							"_lang": "fr",
							"_class": "Pilot",
							"__text": "Autorisé approche à vue piste [RWY], [CAL]."
						},
						{
							"_lang": "en",
							"_class": "ATC",
							"__text": "[CAL], cleared visual approach runway [RWY]."
						},
						{
							"_lang": "en",
							"_class": "Pilot",
							"__text": "Cleared visual approach runway [RWY], [CAL]."
						}
					],
					"_id": "ACCEPTE_MVL_PILOT",
					"_name": "Accepte MVL",
					"_short": "Acceptée",
					"_level": "intermédiaire"
				},
				{
					"para": [
						{
							"_lang": "fr",
							"_class": "Pilot",
							"__text": "Affirm, [CAL]."
						},
						{
							"_lang": "fr",
							"_class": "ATC",
							"__text": "[CAL], autorisé approche à vue piste [RWY], assurez votre séparation avec A 320 devant vous."
						},
						{
							"_lang": "fr",
							"_class": "Pilot",
							"__text": "Autorisé approche à vue piste [RWY], [CAL]."
						},
						{
							"_lang": "en",
							"_class": "Pilot",
							"__text": "Affirm, [CAL]."
						},
						{
							"_lang": "en",
							"_class": "ATC",
							"__text": "[CAL], cleared visual approach runway [RWY], maintain own separation from preceding (Airbus 3_2_0)."
						},
						{
							"_lang": "en",
							"_class": "Pilot",
							"__text": "Cleared visual approach runway [RWY], [CAL]."
						}
					],
					"_id": "ACCEPTE_MVL_TRAFIC",
					"_name": "Accepte MVL",
					"_short": "Trafic",
					"_level": "intermédiaire"
				},
				{
					"para": [
						{
							"_lang": "fr",
							"_class": "Pilot",
							"__text": "Affirm, [CAL]."
						},
						{
							"_lang": "fr",
							"_class": "ATC",
							"__text": "[CAL], autorisé approche à vue piste [RWY]."
						},
						{
							"_lang": "fr",
							"_class": "Pilot",
							"__text": "Autorisé approche à vue piste [RWY], [CAL]."
						},
						{
							"_lang": "en",
							"_class": "Pilot",
							"__text": "Affirm, [CAL]."
						},
						{
							"_lang": "en",
							"_class": "ATC",
							"__text": "[CAL], cleared visual approach runway [RWY]."
						},
						{
							"_lang": "en",
							"_class": "Pilot",
							"__text": "Cleared visual approach runway [RWY], [CAL]."
						}
					],
					"_id": "ACCEPTE_MVL",
					"_name": "Accepte MVL",
					"_short": "Autorisée",
					"_level": "intermédiaire"
				},
				{
					"para": [
						{
							"_lang": "fr",
							"_class": "Pilot",
							"__text": "Négatif, [CAL]."
						},
						{
							"_lang": "fr",
							"_class": "ATC",
							"__text": "[CAL], autorisé approche I_L_S piste [RWY]."
						},
						{
							"_lang": "fr",
							"_class": "Pilot",
							"__text": "Autorisé approche I_L_S piste [RWY], [CAL]."
						},
						{
							"_lang": "en",
							"_class": "Pilot",
							"__text": "Negative, [CAL]."
						},
						{
							"_lang": "en",
							"_class": "ATC",
							"__text": "[CAL], cleared I_L_S approach runway [RWY]."
						},
						{
							"_lang": "en",
							"_class": "Pilot",
							"__text": "Cleared I_L_S approach runway [RWY], [CAL]."
						}
					],
					"_id": "REFUSE_MVL",
					"_name": "Refuse MVL",
					"_short": "Refusée",
					"_level": "intermédiaire"
				},
				{
					"para": [
						{
							"_lang": "fr",
							"_class": "ATC",
							"__text": "[CAL], rappelez à l'ouverture (droite)."
						},
						{
							"_lang": "fr",
							"_class": "Pilot",
							"__text": "Je rappelle à l'ouverture droite, [CAL]."
						},
						{
							"_lang": "en",
							"_class": "ATC",
							"__text": "[CAL], report breaking (right)."
						},
						{
							"_lang": "en",
							"_class": "Pilot",
							"__text": "Reporting breaking (right), [CAL]."
						}
					],
					"_id": "OUVERTURE_VPT",
					"_name": "Ouverture VPT",
					"_short": "Ouv VPT",
					"_level": "intermédiaire"
				},
				{
					"para": [
						{
							"_lang": "fr",
							"_class": "ATC",
							"__text": "[CAL], piste [RWY], autorisé atterrissage, vent 0_50 degrés 10 nœuds."
						},
						{
							"_lang": "fr",
							"_class": "Pilot",
							"__text": "Piste [RWY], j'atterris, [CAL]."
						},
						{
							"_lang": "en",
							"_class": "ATC",
							"__text": "[CAL], runway [RWY], cleared to land, wind 0_5_0 degrees, 10 knots."
						},
						{
							"_lang": "en",
							"_class": "Pilot",
							"__text": "Runway [RWY], landing, [CAL]."
						}
					],
					"_id": "ATTERRISSAGE_AUTORISE",
					"_name": "Autorisé",
					"_short": "Autorisée",
					"_level": "débutant"
				},
				{
					"para": [
						{
							"_lang": "fr",
							"_class": "ATC",
							"__text": "[CAL], piste [RWY], autorisé atterrissage, vent 0_50 degrés 10 nœuds, dégagement rapide si possible."
						},
						{
							"_lang": "fr",
							"_class": "Pilot",
							"__text": "Piste [RWY], j'atterris, [CAL]."
						},
						{
							"_lang": "en",
							"_class": "ATC",
							"__text": "[CAL], runway [RWY], cleared to land, wind 0_5_0 degrees, 10 knots, expedite vacating if possible."
						},
						{
							"_lang": "en",
							"_class": "Pilot",
							"__text": "Runway [RWY], landing, [CAL]."
						}
					],
					"_id": "ATTERRISSAGE_VITESSE_CONTROLEE",
					"_name": "Autorisé, dégagement rapide",
					"_short": "Dégagement",
					"_level": "intermédiaire"
				},
				{
					"para": [
						{
							"_lang": "fr",
							"_class": "ATC",
							"__text": "[CAL], remettez les gaz, tournez à (droite) cap 220, montez à [NIV] pieds."
						},
						{
							"_lang": "fr",
							"_class": "Pilot",
							"__text": "Je remets les gaz, tourne à (droite) cap 220 et monte à [NIV] pieds, [CAL]."
						},
						{
							"_lang": "en",
							"_class": "ATC",
							"__text": "[CAL], go around, turn (right) 220 degrees, climb [NIV] feet."
						},
						{
							"_lang": "en",
							"_class": "Pilot",
							"__text": "Going around, turning (right) 220 degrees, climbing [NIV] feet, [CAL]."
						}
					],
					"_id": "REMISE_GAZ",
					"_name": "Remise de gaz (ATC)",
					"_short": "RdG ATC",
					"_level": "débutant"
				},
				{
					"para": [
						{
							"_lang": "fr",
							"_class": "Pilot",
							"__text": "[CAL], je remets les gaz."
						},
						{
							"_lang": "fr",
							"_class": "ATC",
							"__text": "[CAL], rappelez à [NIV] pieds."
						},
						{
							"_lang": "en",
							"_class": "Pilot",
							"__text": "[CAL], going around."
						},
						{
							"_lang": "en",
							"_class": "ATC",
							"__text": "[CAL], report [NIV] feet."
						}
					],
					"_id": "REMISE_GAZ_PILOTE",
					"_name": "Remise de gaz (Pilote)",
					"_short": "RdG Pilote",
					"_level": "débutant"
				},
				{
					"para": [
						{
							"_lang": "fr",
							"_class": "ATC",
							"__text": "[CAL], rappelez piste dégagée."
						},
						{
							"_lang": "fr",
							"_class": "Pilot",
							"__text": "Roger, [CAL]."
						},
						{
							"_lang": "en",
							"_class": "ATC",
							"__text": "[CAL], report runway vacating."
						},
						{
							"_lang": "en",
							"_class": "Pilot",
							"__text": "Roger, [CAL]."
						}
					],
					"_id": "DEGAGEMENT_STANDARD",
					"_name": "Dégagement standard",
					"_short": "Dégagement",
					"_level": "débutant"
				},
				{
					"para": [
						{
							"_lang": "fr",
							"_class": "ATC",
							"__text": "[CAL], dégagez première à (gauche)."
						},
						{
							"_lang": "fr",
							"_class": "Pilot",
							"__text": "Première à (gauche), [CAL]."
						},
						{
							"_lang": "en",
							"_class": "ATC",
							"__text": "[CAL], vacate first (left)."
						},
						{
							"_lang": "en",
							"_class": "Pilot",
							"__text": "First (left), [CAL]."
						}
					],
					"_id": "DEGAGEMENT_SORTIE",
					"_name": "Dégagement particulier",
					"_short": "Dégagement",
					"_level": "intermédiaire"
				},
				{
					"para": [
						{
							"_lang": "fr",
							"_class": "ATC",
							"__text": "[CAL], faites un 180, remontez la piste puis dégagez première à (droite)."
						},
						{
							"_lang": "fr",
							"_class": "Pilot",
							"__text": "Je remonte la piste puis première à (droite), [CAL]."
						},
						{
							"_lang": "en",
							"_class": "ATC",
							"__text": "[CAL], make a 180, backtrack runway then vacate first (right)."
						},
						{
							"_lang": "en",
							"_class": "Pilot",
							"__text": "Backtracking runway then first (right), [CAL]."
						}
					],
					"_id": "DEGAGEMENT_REMONTEE",
					"_name": "Remontée et dégagement",
					"_short": "Remontée dégag",
					"_level": "intermédiaire"
				},
				{
					"para": [
						{
							"_lang": "fr",
							"_class": "ATC",
							"__text": "[CAL], roulez poste [POS] via [VOI] et veiller  la fréquence, au revoir."
						},
						{
							"_lang": "fr",
							"_class": "Pilot",
							"__text": "Je roule poste [POS] via [VOI], [CAL]."
						},
						{
							"_lang": "en",
							"_class": "ATC",
							"__text": "[CAL], taxi stand [POS] via [VOI] and monitor the frequency, good day."
						},
						{
							"_lang": "en",
							"_class": "Pilot",
							"__text": "Taxiing stand [POS] via [VOI], [CAL]."
						}
					],
					"_id": "PARKING",
					"_name": "Parking",
					"_short": "Parking",
					"_level": "débutant"
				},
				{
					"para": [
						{
							"_lang": "fr",
							"_class": "Pilot",
							"__text": "[DEP] [NGND], [CAL], au parking, pour quitter."
						},
						{
							"_lang": "fr",
							"_class": "ATC",
							"__text": "[CAL], vous pouvez quitter la fréquence, au revoir."
						},
						{
							"_lang": "en",
							"_class": "Pilot",
							"__text": "[DEP] [NGND], [CAL], au parking, pour quitter."
						},
						{
							"_lang": "en",
							"_class": "ATC",
							"__text": "[CAL], you can leave frequency, good day."
						}
					],
					"_id": "QUITTER",
					"_name": "Quitter",
					"_short": "Quitter",
					"_level": "débutant"
				},
				{
					"para": [
						{
							"_lang": "fr",
							"_class": "ATC",
							"__text": "[CAL], maintenez position avant la prochaine intersection pour laisser passer un airbus 321."
						},
						{
							"_lang": "fr",
							"_class": "Pilot",
							"__text": "Je maintiens position avant la prochaine intersection, [CAL]."
						},
						{
							"_lang": "en",
							"_class": "ATC",
							"__text": "[CAL], hold short of next intersection to give way to the Airbus 321."
						},
						{
							"_lang": "en",
							"_class": "Pilot",
							"__text": "Holding short of next intersection, [CAL]."
						}
					],
					"_id": "TRAFIC_SOL",
					"_name": "Priorité trafic",
					"_short": "Trafic",
					"_level": "intermédiaire"
				},
				{
					"para": [
						{
							"_lang": "fr",
							"_class": "ATC",
							"__text": "[CAL], traversez piste (04 gauche)."
						},
						{
							"_lang": "fr",
							"_class": "Pilot",
							"__text": "Je traverse piste (04 gauche), [CAL]."
						},
						{
							"_lang": "en",
							"_class": "ATC",
							"__text": "[CAL], cross runway (04 left)."
						},
						{
							"_lang": "en",
							"_class": "Pilot",
							"__text": "Crossing runway (04 left), [CAL]."
						}
					],
					"_id": "TRAVERSER_PISTE",
					"_name": "Traversée de piste",
					"_short": "Trav ATC",
					"_level": "débutant"
				},
				{
					"para": [
						{
							"_lang": "fr",
							"_class": "Pilot",
							"__text": "[CAL], demande traversée piste (04 gauche)."
						},
						{
							"_lang": "fr",
							"_class": "ATC",
							"__text": "[CAL], traversez piste (04 gauche)."
						},
						{
							"_lang": "fr",
							"_class": "Pilot",
							"__text": "Je traverse la piste (04 gauche), [CAL]."
						},
						{
							"_lang": "en",
							"_class": "Pilot",
							"__text": "[CAL], request to cross runway (04 left)."
						},
						{
							"_lang": "en",
							"_class": "ATC",
							"__text": "[CAL], cross runway (04 left)."
						},
						{
							"_lang": "en",
							"_class": "Pilot",
							"__text": "Crossing runway (04 left), [CAL]."
						}
					],
					"_id": "DEMANDE_TRAVERSEE_PISTE",
					"_name": "Demande de traversée",
					"_short": "Trav Pil",
					"_level": "débutant"
				},
				{
					"para": [
						{
							"_lang": "fr",
							"_class": "ATC",
							"__text": "[CAL], traversez rapidement piste (04 gauche), trafic (Airbus 350) 4 nautiques finales, rappelez piste dégagée."
						},
						{
							"_lang": "fr",
							"_class": "Pilot",
							"__text": "Je traverse rapidement piste (04 gauche) et rappelle piste dégagée, [CAL]."
						},
						{
							"_lang": "en",
							"_class": "ATC",
							"__text": "[CAL], expedite crossing runway (04 left), traffic Airbus 350, 4 miles on final, report runway vacated."
						},
						{
							"_lang": "en",
							"_class": "Pilot",
							"__text": "Expediting crossing runway (04 left), reporting runway vacated, [CAL]."
						}
					],
					"_id": "ACCELERER_TRAVERSEE_PISTE",
					"_name": "Accélérer la traversée",
					"_short": "Accélérer",
					"_level": "intermédiaire"
				},
				{
					"para": [
						{
							"_lang": "fr",
							"_class": "ATC",
							"__text": "[CAL], accusez réception par ident."
						},
						{
							"_lang": "en",
							"_class": "ATC",
							"__text": "[CAL], if you read me, squawk ident."
						}
					],
					"_id": "ACCUSEZ",
					"_name": "Accuser réception",
					"_short": "Accuser",
					"_level": "débutant"
				},
				{
					"para": [
						{
							"_lang": "fr",
							"_class": "Pilot",
							"__text": "[CAL], parlez plus lentement."
						},
						{
							"_lang": "en",
							"_class": "Pilot",
							"__text": "[CAL], speak slower."
						}
					],
					"_id": "LENTEMENT",
					"_name": "Parler lentement",
					"_short": "Lentement",
					"_level": "débutant"
				},
				{
					"para": [
						{
							"_lang": "fr",
							"_class": "ATC",
							"__text": "[CAL], collationnez."
						},
						{
							"_lang": "en",
							"_class": "ATC",
							"__text": "[CAL], read back."
						}
					],
					"_id": "REPETEA",
					"_name": "Collationner",
					"_short": "Collationner",
					"_level": "débutant"
				},
				{
					"para": [
						{
							"_lang": "fr",
							"_class": "Pilot",
							"__text": "[CAL], répétez."
						},
						{
							"_lang": "en",
							"_class": "Pilot",
							"__text": "[CAL], say again."
						}
					],
					"_id": "REPETEP",
					"_name": "Répéter",
					"_short": "Répéter",
					"_level": "débutant"
				},
				{
					"para": [
						{
							"_lang": "fr",
							"_class": "ATC",
							"__text": "[CAL], alignez-vous piste [RWY], autorisé décollage, vent 0_50 degrés 10 nœuds."
						},
						{
							"_lang": "fr",
							"_class": "Pilot",
							"__text": "Je m'aligne piste [RWY] et je décolle, [CAL]."
						},
						{
							"_lang": "en",
							"_class": "ATC",
							"__text": "[CAL], line up runway [RWY], cleared for take-off, wind 0_5_0 degrees, 10 knots."
						},
						{
							"_lang": "en",
							"_class": "Pilot",
							"__text": "Lining up runway [RWY] and taking-off, [CAL]."
						}
					],
					"_id": "ALIGNEMENT_DECO",
					"_name": "Alignement et décollage",
					"_short": "Alig + décol",
					"_level": "débutant"
				},
				{
					"para": [
						{
							"_lang": "fr",
							"_class": "ATC",
							"__text": "[CAL], piste [RWY], autorisé décollage, vent 0_50 degrés 10 nœuds."
						},
						{
							"_lang": "fr",
							"_class": "Pilot",
							"__text": "Piste [RWY], je décolle, [CAL]."
						},
						{
							"_lang": "en",
							"_class": "ATC",
							"__text": "[CAL], runway [RWY], cleared for take-off, wind 0_5_0 degrees, 10 knots."
						},
						{
							"_lang": "en",
							"_class": "Pilot",
							"__text": "Runway [RWY], taking-off, [CAL]."
						}
					],
					"_id": "DECOL_AUTO",
					"_name": "Décollage déjà aligné",
					"_short": "Autorisé",
					"_level": "débutant"
				},
				{
					"para": [
						{
							"_lang": "fr",
							"_class": "ATC",
							"__text": "[CAL], stoppez immédiatement, [CAL], stoppez immédiatement, un véhicule sur la piste."
						},
						{
							"_lang": "en",
							"_class": "ATC",
							"__text": "[CAL], stop immediately, [CAL], stop immediately, vehicle on runway."
						},
						{
							"_lang": "fr",
							"_class": "Pilot",
							"__text": "Je stoppe immédiatement, [CAL]."
						},
						{
							"_lang": "en",
							"_class": "Pilot",
							"__text": "Stopping immediately, [CAL]."
						}
					],
					"_id": "DECOL_STOPPE",
					"_name": "Décollage stoppé",
					"_short": "Stop",
					"_level": "intermédiaire"
				},
				{
					"para": [
						{
							"_lang": "fr",
							"_class": "ATC",
							"__text": "[CAL], maintenez position, annulez le décollage, je répète, annulez le décollage, (A_T_R en remise de gaz)"
						},
						{
							"_lang": "en",
							"_class": "ATC",
							"__text": "[CAL], hold position, cancel take-off, I say again cancel take-off, (A_T_R going around)."
						},
						{
							"_lang": "fr",
							"_class": "Pilot",
							"__text": "Je maintiens position, [CAL]."
						},
						{
							"_lang": "en",
							"_class": "Pilot",
							"__text": "Holding position, [CAL]."
						}
					],
					"_id": "DECOL_ANNULE",
					"_name": "Décollage annulé",
					"_short": "Annulé",
					"_level": "débutant"
				},
				{
					"para": [
						{
							"_lang": "fr",
							"_class": "Pilot",
							"__text": "[CAL], j'interromps décollage (piste [RWY]{Indiquer la piste si plusieurs pistes possibles au décollage})."
						},
						{
							"_lang": "en",
							"_class": "Pilot",
							"__text": "[CAL], aborting take-off(, runway [RWY]{Indiquer la piste si plusieurs pistes possibles au décollage})."
						}
					],
					"_id": "DECOL_INTEROMPU",
					"_name": "Décollage interrompu",
					"_short": "Interrompu",
					"_level": "intermédiaire"
				},
				{
					"para": [
						{
							"_lang": "fr",
							"_class": "ATC",
							"__text": "[CAL], roulez avec précaution."
						},
						{
							"_lang": "en",
							"_class": "ATC",
							"__text": "[CAL], taxi with caution."
						}
					],
					"_id": "DECELERE",
					"_name": "Décélération roulage",
					"_short": "Décélération",
					"_level": "intermédiaire"
				},
				{
					"para": [
						{
							"_lang": "fr",
							"_class": "ATC",
							"__text": "[CAL], expédiez le roulage."
						},
						{
							"_lang": "en",
							"_class": "ATC",
							"__text": "[CAL], expedite taxi."
						}
					],
					"_id": "ACCELERE",
					"_name": "Accélération roulage",
					"_short": "Accélération",
					"_level": "intermédiaire"
				},
				{
					"para": [
						{
							"_lang": "fr",
							"_class": "ATC",
							"__text": "[CAL], avez-vous visuel sur trafic précédent ?"
						},
						{
							"_lang": "fr",
							"_class": "Pilot",
							"__text": "Affirm, [CAL]."
						},
						{
							"_lang": "en",
							"_class": "ATC",
							"__text": "[CAL], have you visual contact on preceding traffic?"
						},
						{
							"_lang": "en",
							"_class": "Pilot",
							"__text": "Affirm, [CAL]."
						}
					],
					"_id": "VISUEL",
					"_name": "Trafic en vue",
					"_short": "Trafic",
					"_level": "intermédiaire"
				},
				{
					"para": [
						{
							"_lang": "fr",
							"_class": "ATC",
							"__text": "[CAL], attention, turbulence de sillage possible."
						},
						{
							"_lang": "fr",
							"_class": "Pilot",
							"__text": "Roger, [CAL]."
						},
						{
							"_lang": "en",
							"_class": "ATC",
							"__text": "[CAL], caution, wake turbulence possibility."
						},
						{
							"_lang": "en",
							"_class": "Pilot",
							"__text": "Roger, [CAL]."
						}
					],
					"_id": "SILLAGE",
					"_name": "Turbulence de sillage",
					"_short": "Turbulence",
					"_level": "intermédiaire"
				},
				{
					"para": [
						{
							"_lang": "fr",
							"_class": "ATC",
							"__text": "[CAL], quel est votre taux de montée ?"
						},
						{
							"_lang": "fr",
							"_class": "Pilot",
							"__text": "Je monte au taux 1800 pieds par minute, [CAL]."
						},
						{
							"_lang": "en",
							"_class": "ATC",
							"__text": "[CAL], say rate of climb?"
						},
						{
							"_lang": "en",
							"_class": "Pilot",
							"__text": "Climbing rate 1800 feet per minute, [CAL]."
						}
					],
					"_id": "TAUX_MONTEE",
					"_name": "Taux de montée",
					"_short": "Taux mont",
					"_level": "intermédiaire"
				},
				{
					"para": [
						{
							"_lang": "fr",
							"_class": "ATC",
							"__text": "[CAL], transpondeur ident."
						},
						{
							"_lang": "fr",
							"_class": "Pilot",
							"__text": "Transpondeur ident, [CAL]."
						},
						{
							"_lang": "en",
							"_class": "ATC",
							"__text": "[CAL], squawk ident."
						},
						{
							"_lang": "en",
							"_class": "Pilot",
							"__text": "Squawk ident, [CAL]."
						}
					],
					"_id": "IDENT",
					"_name": "Identification transpondeur",
					"_short": "Identification",
					"_level": "débutant"
				},
				{
					"_id": "MER_SIMPLE",
					"_name": "MER approuvée",
					"_short": "Approuvée",
					"_level": "débutant",
					"para": [
						{
							"_lang": "fr",
							"_class": "ATC",
							"__text": "[CAL], [POL], mise en route approuvée, départ [STA], montée initiale [NIV], transpondeur [SQU]."
						},
						{
							"_lang": "fr",
							"_class": "Pilot",
							"__text": "Mise en route approuvée, départ [STA], montée initiale [NIV], transpondeur [SQU], [CAL]."
						},
						{
							"_lang": "fr",
							"_class": "ATC",
							"__text": "[CAL], correct, rappelez prêt pour le repoussage sur [DEP] [GND] {ce rappel est nécessaire uniquement en cas de transfert}."
						},
						{
							"_lang": "en",
							"_class": "ATC",
							"__text": "[CAL], [POL], startup approved, [STA] departure, initial climb [NIV], squawk [SQU]."
						},
						{
							"_lang": "en",
							"_class": "Pilot",
							"__text": "Startup approved, [STA] departure, initial climb [NIV], squawk [SQU], [CAL]."
						},
						{
							"_lang": "en",
							"_class": "ATC",
							"__text": "[CAL], correct, report ready for push-back [DEP] [GND] {ce rappel est nécessaire uniquement en cas de transfert}."
						}
					],
					"_levelExact": true
				}
			],
			"orTask": [
				{
					"para": [
						{
							"_lang": "fr",
							"_class": "Pilot",
							"__text": "[DEP] [NDEL], [POL], [CAL] en [POS], demande mise en route pour [ARR], information [INF]."
						},
						{
							"_lang": "en",
							"_class": "Pilot",
							"__text": "[DEP] [NDEL], [POL], [CAL] gate [POS], request startup to [ARR], information [INF]."
						}
					],
					"subgraph": [
						{
							"call": {
								"_class": "option",
								"_refid": "MER_SIMPLE"
							}
						},
						{
							"call": {
								"_class": "option",
								"_refid": "MER_APPROUVEE"
							}
						},
						{
							"call": {
								"_class": "option",
								"_refid": "MER_DIFFEREE"
							}
						},
						{
							"call": {
								"_class": "option",
								"_refid": "MER_OMNI"
							}
						},
						{
							"call": {
								"_class": "option",
								"_refid": "NON_RNAV"
							}
						},
						{
							"call": {
								"_class": "option",
								"_refid": "EST_IL_RNAV"
							}
						}
					],
					"_id": "DEMANDE_MISE_EN_ROUTE",
					"_name": "Mise en route",
					"_short": "MER",
					"_level": "débutant"
				},
				{
					"para": [
						{
							"_lang": "fr",
							"_class": "Pilot",
							"__text": "[DEP] [NGND], [CAL], demande repoussage."
						},
						{
							"_lang": "en",
							"_class": "Pilot",
							"__text": "[DEP] [NGND], [CAL], request push-back."
						}
					],
					"subgraph": [
						{
							"call": {
								"_class": "option",
								"_refid": "REPOUSSAGE_STANDARD"
							}
						},
						{
							"call": {
								"_class": "option",
								"_refid": "REPOUSSAGE_CONDITIONNEL"
							}
						}
					],
					"_repeat": "FALSE",
					"_id": "DEMANDE_REPOUSSAGE",
					"_name": "Repoussage",
					"_short": "Repoussage",
					"_level": "débutant"
				},
				{
					"para": [
						{
							"_lang": "fr",
							"_class": "Pilot",
							"__text": "[CAL], demande roulage."
						},
						{
							"_lang": "en",
							"_class": "Pilot",
							"__text": "[CAL], request taxi."
						}
					],
					"subgraph": [
						{
							"call": {
								"_class": "option",
								"_refid": "ROULAGE_AUTORISE"
							}
						},
						{
							"call": {
								"_class": "option",
								"_refid": "ROULAGE_TRAFIC"
							}
						}
					],
					"_id": "DEMANDE_ROULAGE",
					"_name": "Roulage",
					"_short": "Roulage",
					"_level": "débutant"
				},
				{
					"subgraph": [
						{
							"call": {
								"_class": "option",
								"_refid": "ACCELERE"
							}
						},
						{
							"call": {
								"_class": "option",
								"_refid": "DECELERE"
							}
						},
						{
							"call": {
								"_class": "option",
								"_refid": "TRAFIC_SOL"
							}
						}
					],
					"_id": "TAXI",
					"_name": "Circulation",
					"_short": "Circulation",
					"_level": "débutant"
				},
				{
					"subgraph": [
						{
							"call": {
								"_class": "option",
								"_refid": "TRAFIC_SOL"
							}
						},
						{
							"call": {
								"_class": "option",
								"_refid": "TRAVERSER_PISTE"
							}
						}
					],
					"_id": "TAXI2",
					"_name": "Circulation",
					"_short": "Circulation",
					"_level": "débutant"
				},
				{
					"para": [
						{
							"_lang": "fr",
							"_class": "Pilot",
							"__text": "[DEP] [NTWR], [POL], [CAL], au point d'attente [HLD]."
						},
						{
							"_lang": "en",
							"_class": "Pilot",
							"__text": "[DEP] [NTWR], [POL], [CAL], holding point [HLD]."
						}
					],
					"subgraph": [
						{
							"call": {
								"_class": "option",
								"_refid": "MAINTIEN_ARRET"
							}
						},
						{
							"call": {
								"_class": "info",
								"_refid": "DEMANDE_TRAVERSEE_PISTE"
							}
						},
						{
							"call": {
								"_class": "option",
								"_refid": "TRAVERSER_PISTE"
							}
						},
						{
							"call": {
								"_class": "option",
								"_refid": "ACCELERER_TRAVERSEE_PISTE"
							}
						},
						{
							"call": {
								"_class": "option",
								"_refid": "DECOLLAGE_IMMEDIAT"
							}
						}
					],
					"_id": "CONTACT_TOUR1",
					"_name": "Point d'attente",
					"_short": "Attente",
					"_level": "débutant"
				},
				{
					"subgraph": [
						{
							"call": {
								"_class": "option",
								"_refid": "ALIGNEMENT"
							}
						},
						{
							"call": {
								"_class": "option",
								"_refid": "ALIGNEMENT_POS2"
							}
						},
						{
							"call": {
								"_class": "option",
								"_refid": "ALIGNEMENT_APRES_AVION_FINAL"
							}
						},
						{
							"call": {
								"_class": "option",
								"_refid": "REMONTEE_PISTE"
							}
						}
					],
					"_repeat": "FALSE",
					"_id": "TYPE_ALIGNEMENT",
					"_name": "Alignement",
					"_short": "Alignement",
					"_level": "débutant"
				},
				{
					"subgraph": [
						{
							"call": {
								"_class": "option",
								"_refid": "DECOL_AUTO"
							}
						},
						{
							"call": {
								"_class": "option",
								"_refid": "ALIGNEMENT_DECO"
							}
						},
						{
							"call": {
								"_class": "option",
								"_refid": "DECOL_ANNULE"
							}
						},
						{
							"call": {
								"_class": "option",
								"_refid": "DECOL_STOPPE"
							}
						},
						{
							"call": {
								"_class": "info",
								"_refid": "DECOL_INTEROMPU"
							}
						}
					],
					"_id": "DECOLLAGE",
					"_name": "Décollage",
					"_short": "Décollage",
					"_level": "débutant"
				},
				{
					"para": [
						{
							"_lang": "fr",
							"_class": "Pilot",
							"__text": "[FIR] [NCTR], [CAL], direct [WPT] niveau [NIV]."
						},
						{
							"_lang": "en",
							"_class": "Pilot",
							"__text": "[FIR] [NCTR], [CAL], direct [WPT] level [NIV]."
						},
						{
							"_lang": "fr",
							"_class": "ATC",
							"__text": "[CAL], [FIR] [NCTR], [POL], identifié, poursuivez."
						},
						{
							"_lang": "en",
							"_class": "ATC",
							"__text": "[CAL], [FIR] [NCTR], [POL], identified, continue."
						}
					],
					"_id": "CONTACT_CTR",
					"_name": "Contact en route",
					"_short": "Contact CTR",
					"_level": "débutant"
				},
				{
					"para": [
						{
							"_lang": "fr",
							"_class": "Pilot",
							"__text": "[DEP] [NAPP], [POL], [CAL], départ [STA], je monte niveau [NIV]."
						},
						{
							"_lang": "en",
							"_class": "Pilot",
							"__text": "[DEP] [NAPP], [POL], [CAL], [STA] departure, climbing level [NIV]."
						}
					],
					"subgraph": [
						{
							"call": {
								"_class": "option",
								"_refid": "CONFIRMATION_SID"
							}
						},
						{
							"call": {
								"_class": "option",
								"_refid": "DIRECT_WPT"
							}
						},
						{
							"call": {
								"_class": "option",
								"_refid": "MONTEE_DIFFEREE"
							}
						}
					],
					"_id": "CONTACT_APP",
					"_name": "Contact approche",
					"_short": "Contact APP",
					"_level": "débutant"
				},
				{
					"para": [
						{
							"_lang": "fr",
							"_class": "Pilot",
							"__text": "[DEP] [NTWR], [CAL], courte finale piste [RWY]."
						},
						{
							"_lang": "en",
							"_class": "Pilot",
							"__text": "[DEP] [NTWR], [CAL], final runway [RWY]."
						},
						{
							"_lang": "fr",
							"_class": "ATC",
							"__text": "[CAL], poursuivez approche piste [RWY]."
						},
						{
							"_lang": "en",
							"_class": "ATC",
							"__text": "[CAL], continue approach runway [RWY]."
						}
					],
					"_id": "CONTACT_TWR",
					"_name": "Contact tour",
					"_short": "Contact TWR",
					"_level": "débutant"
				},
				{
					"subgraph": [
						{
							"call": {
								"_class": "option",
								"_refid": "DIRECT"
							}
						},
						{
							"call": {
								"_class": "option",
								"_refid": "ROUTE_CONTROLEUR"
							}
						}
					],
					"_id": "ROUTE",
					"_name": "Nouvelle route",
					"_short": "Route",
					"_level": "intermédiaire"
				},
				{
					"para": [
						{
							"_lang": "fr",
							"_class": "Pilot",
							"__text": "[CAL], demande changement de route via [WPT]."
						},
						{
							"_lang": "en",
							"_class": "Pilot",
							"__text": "[CAL], request route amendment via [WPT]."
						},
						{
							"_lang": "fr",
							"_class": "ATC",
							"__text": "[CAL], stand-by."
						},
						{
							"_lang": "en",
							"_class": "ATC",
							"__text": "[CAL], stand-by."
						}
					],
					"subgraph": [
						{
							"call": {
								"_class": "option",
								"_refid": "ROUTE_POSITIVE"
							}
						},
						{
							"call": {
								"_class": "option",
								"_refid": "ROUTE_NEGATIVE"
							}
						}
					],
					"_id": "ROUTE_PILOTE",
					"_name": "Changement route",
					"_short": "Route",
					"_level": "intermédiaire"
				},
				{
					"subgraph": [
						{
							"call": {
								"_class": "option",
								"_refid": "TRANSFERT_SIMPLE_CTR"
							}
						},
						{
							"call": {
								"_class": "option",
								"_refid": "TRANSFERT_UNICOM"
							}
						}
					],
					"_id": "TRANSFERT_CTR",
					"_name": "Transfert en route",
					"_short": "Tr CTR",
					"_level": "débutant"
				},
				{
					"subgraph": [
						{
							"call": {
								"_class": "option",
								"_refid": "TRANSFERT_SIMPLE"
							}
						},
						{
							"call": {
								"_class": "option",
								"_refid": "TRANSFERT_UNICOM"
							}
						}
					],
					"_id": "TRANSFERT_APP2",
					"_name": "Transfert approche",
					"_short": "Tr APP",
					"_level": "débutant"
				},
				{
					"subgraph": [
						{
							"call": {
								"_class": "option",
								"_refid": "TRANSFERT_SIMPLE"
							}
						},
						{
							"call": {
								"_class": "option",
								"_refid": "TRANSFERT_UNICOM"
							}
						}
					],
					"_id": "TRANSFERT_APP",
					"_name": "Transfert approche",
					"_short": "Tr APP",
					"_level": "débutant"
				},
				{
					"subgraph": [
						{
							"call": {
								"_class": "option",
								"_refid": "TRAFIC"
							}
						},
						{
							"call": {
								"_class": "option",
								"_refid": "VITESSE"
							}
						}
					],
					"_id": "REGULATION",
					"_name": "Régulation et trafic",
					"_short": "Régulation",
					"_level": "intermédiaire"
				},
				{
					"subgraph": [
						{
							"call": {
								"_class": "option",
								"_refid": "TRAFIC"
							}
						},
						{
							"call": {
								"_class": "option",
								"_refid": "VITESSE"
							}
						}
					],
					"_id": "REGULATIONBIS",
					"_name": "Régulation et trafic",
					"_short": "Régulation",
					"_level": "intermédiaire"
				},
				{
					"para": [
						{
							"_lang": "fr",
							"_class": "Pilot",
							"__text": "[ARR], [POL], [CAL] niveau [NIV], direct [WPT]."
						},
						{
							"_lang": "en",
							"_class": "Pilot",
							"__text": "[ARR], [POL], [CAL] level [NIV], direct [WPT]."
						}
					],
					"subgraph": [
						{
							"call": {
								"_class": "option",
								"_refid": "APPROCHE_STAR"
							}
						},
						{
							"call": {
								"_class": "option",
								"_refid": "APPROCHE_DIRECT"
							}
						},
						{
							"call": {
								"_class": "option",
								"_refid": "DESCENTE_IMMEDIATE"
							}
						},
						{
							"call": {
								"_class": "option",
								"_refid": "DESCENTE_DELAI"
							}
						}
					],
					"_id": "DESCENTE",
					"_name": "Descente",
					"_short": "Descente",
					"_level": "débutant"
				},
				{
					"para": [
						{
							"_lang": "fr",
							"_class": "ATC",
							"__text": "[CAL], annulez approche cause F_O_D, maintenez [NIV], prévoyez guidage I_L_S piste [RWY]."
						},
						{
							"_lang": "en",
							"_class": "ATC",
							"__text": "[CAL], cancel approach due F_O_D, maintain [NIV], expect vectoring I_L_S runway [RWY]."
						},
						{
							"_lang": "fr",
							"_class": "Pilot",
							"__text": "Approche annulée, je maintiens [NIV], prévois guidage I_L_S piste [RWY]. [CAL]."
						},
						{
							"_lang": "en",
							"_class": "Pilot",
							"__text": "Approach cancelled, maintening [NIV], expecting vectoring I_L_S runway, [CAL]."
						}
					],
					"subgraph": [
						{
							"call": {
								"_class": "option",
								"_refid": "CHANGEMENT_CAP"
							}
						},
						{
							"call": {
								"_class": "option",
								"_refid": "DESCENTE_IMMEDIATE"
							}
						},
						{
							"call": {
								"_class": "option",
								"_refid": "CHANGEMENT_NIVEAU_CAP"
							}
						},
						{
							"call": {
								"_class": "option",
								"_refid": "INTERCEPTION_ILS"
							}
						},
						{
							"call": {
								"_class": "option",
								"_refid": "REDUCTION_VITESSE"
							}
						}
					],
					"_id": "GUIDAGE_RADAR",
					"_name": "Guidage",
					"_short": "Radar",
					"_level": "intermédiaire"
				},
				{
					"subgraph": [
						{
							"call": {
								"_class": "option",
								"_refid": "ATTENTE_PUBLIEE"
							}
						},
						{
							"call": {
								"_class": "option",
								"_refid": "ATTENTE_PARAMETRES"
							}
						}
					],
					"_id": "ATTENTE",
					"_name": "Circuit d'attente",
					"_short": "Attente",
					"_level": "intermédiaire"
				},
				{
					"para": [
						{
							"_lang": "fr",
							"_class": "ATC",
							"__text": "[CAL], autorisé approche I_L_S piste (contre-QFU), suivie d'une V_P_T piste [RWY]."
						},
						{
							"_lang": "fr",
							"_class": "Pilot",
							"__text": "Autorisé approche I_L_S piste (contre-QFU), suivie d'une V_P_T piste [RWY], [CAL]."
						},
						{
							"_lang": "en",
							"_class": "ATC",
							"__text": "[CAL], cleared I_L_S approach runway (contre-QFU), followed by V_P_T runway [RWY]."
						},
						{
							"_lang": "en",
							"_class": "Pilot",
							"__text": "Cleared I_L_S approach runway (contre-QFU), followed by V_P_T runway [RWY], [CAL]."
						}
					],
					"_id": "APPROCHE_VPT",
					"_name": "Approche VPT",
					"_short": "VPT",
					"_level": "intermédiaire"
				},
				{
					"para": [
						{
							"_lang": "fr",
							"_class": "ATC",
							"__text": "[CAL], acceptez-vous approche à vue piste [RWY] ?"
						},
						{
							"_lang": "en",
							"_class": "ATC",
							"__text": "[CAL], do you accept visual approach runway [RWY] ?"
						}
					],
					"subgraph": [
						{
							"call": {
								"_class": "info",
								"_refid": "ACCEPTE_MVL"
							}
						},
						{
							"call": {
								"_class": "option",
								"_refid": "TRAFIC_MVL"
							}
						},
						{
							"call": {
								"_class": "info",
								"_refid": "REFUSE_MVL"
							}
						}
					],
					"_id": "APPROCHE_VUE",
					"_name": "Approche à vue",
					"_short": "A vue",
					"_level": "intermédiaire"
				},
				{
					"para": [
						{
							"_lang": "fr",
							"_class": "Pilot",
							"__text": "[CAL], demande approche à vue piste [RWY]."
						},
						{
							"_lang": "en",
							"_class": "Pilot",
							"__text": "[CAL], request visual approach runway [RWY]."
						}
					],
					"subgraph": [
						{
							"call": {
								"_class": "option",
								"_refid": "ACCEPTE_MVL_PILOT"
							}
						},
						{
							"call": {
								"_class": "option",
								"_refid": "TRAFIC_MVL"
							}
						}
					],
					"_id": "APPROCHE_VUE_PILOT",
					"_name": "Approche à vue",
					"_short": "A vue",
					"_level": "intermédiaire"
				},
				{
					"subgraph": [
						{
							"call": {
								"_class": "option",
								"_refid": "APPROCHE_AUTORISE"
							}
						},
						{
							"call": {
								"_class": "option",
								"_refid": "APPROCHE_VPT"
							}
						}
					],
					"_id": "APPROCHE",
					"_name": "Approche standard",
					"_short": "Approche",
					"_level": "débutant"
				},
				{
					"subgraph": [
						{
							"call": {
								"_class": "option",
								"_refid": "OUVERTURE_VPT"
							}
						},
						{
							"call": {
								"_class": "option",
								"_refid": "ATTERRISSAGE_AUTORISE"
							}
						},
						{
							"call": {
								"_class": "option",
								"_refid": "ATTERRISSAGE_VITESSE_CONTROLEE"
							}
						},
						{
							"call": {
								"_class": "option",
								"_refid": "REMISE_GAZ"
							}
						},
						{
							"call": {
								"_class": "info",
								"_refid": "REMISE_GAZ_PILOTE"
							}
						}
					],
					"_id": "ATTERRISSAGE",
					"_name": "Atterrissage",
					"_short": "Atterrissage",
					"_level": "débutant"
				},
				{
					"para": [
						{
							"_lang": "fr",
							"_class": "Pilot",
							"__text": "[CAL], vitesse contrôlée."
						},
						{
							"_lang": "en",
							"_class": "Pilot",
							"__text": "[CAL], speed under control."
						}
					],
					"subgraph": [
						{
							"call": {
								"_class": "option",
								"_refid": "DEGAGEMENT_STANDARD"
							}
						},
						{
							"call": {
								"_class": "option",
								"_refid": "DEGAGEMENT_SORTIE"
							}
						},
						{
							"call": {
								"_class": "option",
								"_refid": "DEGAGEMENT_REMONTEE"
							}
						}
					],
					"_id": "DEGAGEMENT",
					"_name": "Vitesse contrôlée",
					"_short": "Vit contrôlée",
					"_level": "débutant"
				}
			]
		}
	}
}